{"lastUsed":1654244772901,"path":"C:\/java","projectCount":13,"recentFiles":[{"path":"\/work1\/src\/work1","parentWorkspace":"C:\/java","name":"MainClass.java","lastModified":1654228177567,"locationURI":"file:\/C:\/java\/work1\/src\/work1\/MainClass.java"},{"path":"\/Test\/src","parentWorkspace":"C:\/java","name":"MainClass.java","lastModified":1654148424686},{"path":"\/Sample01\/src\/sample01","parentWorkspace":"C:\/java","name":"MainClass.java","lastModified":1654214559498},{"path":"\/sample05\/src\/sample05","parentWorkspace":"C:\/java","name":"MainClass.java","lastModified":1654218536535,"locationURI":"file:\/C:\/java\/sample05\/src\/sample05\/MainClass.java"},{"path":"\/Sample04\/src\/sample04","parentWorkspace":"C:\/java","name":"MainClass.java","lastModified":1654214559498,"locationURI":"file:\/C:\/java\/Sample04\/src\/sample04\/MainClass.java"},{"path":"\/work1\/src\/work1","parentWorkspace":"C:\/java","name":"Main.java","lastModified":1654235351386,"locationURI":"file:\/C:\/java\/work1\/src\/work1\/Main.java"},{"path":"\/work2\/src\/work2","parentWorkspace":"C:\/java","name":"MainClass.java","lastModified":1654240255629,"locationURI":"file:\/C:\/java\/work2\/src\/work2\/MainClass.java"},{"path":"\/sample06\/src\/sample06","parentWorkspace":"C:\/java","name":"MainClass.java","lastModified":1654224772092,"locationURI":"file:\/C:\/java\/sample06\/src\/sample06\/MainClass.java"},{"path":"\/Sample02\/src\/sample02","parentWorkspace":"C:\/java","name":"MainClass.java","lastModified":1654214559498,"locationURI":"file:\/C:\/java\/Sample02\/src\/sample02\/MainClass.java"},{"path":"\/work\/src\/work","parentWorkspace":"C:\/java","name":"MainClass.java","lastModified":1654214559498,"locationURI":"file:\/C:\/java\/work\/src\/work\/MainClass.java"},{"path":"\/smaple08\/src\/smaple08","parentWorkspace":"C:\/java","name":"MainClass.java","lastModified":1654224736813,"locationURI":"file:\/C:\/java\/smaple08\/src\/smaple08\/MainClass.java"},{"path":"\/sample07\/src\/sample07","parentWorkspace":"C:\/java","name":"MainClass.java","lastModified":1654222521448,"locationURI":"file:\/C:\/java\/sample07\/src\/sample07\/MainClass.java"},{"path":"\/Sample03\/src\/sample03","parentWorkspace":"C:\/java","name":"MainClass.java","lastModified":1654154498953,"locationURI":"file:\/C:\/java\/Sample03\/src\/sample03\/MainClass.java"},{"path":"\/work3\/src\/work3","parentWorkspace":"C:\/java","name":"MainClass.java","lastModified":1654244773023,"locationURI":"file:\/C:\/java\/work3\/src\/work3\/MainClass.java"}]}